AUTHORS.rst
CONTRIBUTING.rst
HISTORY.rst
LICENSE
MANIFEST.in
README.md
setup.py
ipynb2viewer/__init__.py
ipynb2viewer/ipynb2viewer.py
ipynb2viewer.egg-info/PKG-INFO
ipynb2viewer.egg-info/SOURCES.txt
ipynb2viewer.egg-info/dependency_links.txt
ipynb2viewer.egg-info/entry_points.txt
ipynb2viewer.egg-info/not-zip-safe
ipynb2viewer.egg-info/requires.txt
ipynb2viewer.egg-info/top_level.txt