Metadata-Version: 1.1
Name: ipynb2viewer
Version: 0.1.1
Summary: Post IPython notebook files to nbviewer. IPython notebook content will be posted to gist.github.com.
Home-page: https://github.com/kracekumar/ipynb2viewer
Author: kracekumar
Author-email: me@kracekumar.com
License: BSD
Keywords: ipynb2viewer,ipython
Platform: UNKNOWN
Classifier: Development Status :: 2 - Pre-Alpha
Classifier: Intended Audience :: Developers
Classifier: License :: OSI Approved :: BSD License
Classifier: Natural Language :: English
Classifier: Programming Language :: Python :: 2
Classifier: Programming Language :: Python :: 2.6
Classifier: Programming Language :: Python :: 2.7
Classifier: Programming Language :: Python :: 3
Classifier: Programming Language :: Python :: 3.3
